tuxgo/__init__.py
tuxgo/__main__.py
tuxgo/ast.py
tuxgo/badges.py
tuxgo/blocks.py
tuxgo/bluetooth.py
tuxgo/detector.py
tuxgo/engine.py
tuxgo/game_bt.py
tuxgo/game_sim.py
tuxgo/http_server.py
tuxgo/markers.py
tuxgo/parser.py
tuxgo/theme.py
tuxgo/utils.py
tuxgo-0a0.dist-info/COPYING
tuxgo-0a0.dist-info/METADATA
tuxgo-0a0.dist-info/WHEEL
tuxgo-0a0.dist-info/top_level.txt
tuxgo-0a0.dist-info/RECORD
